airless/google/cloud/storage/__init__.py
airless/google/cloud/storage/hook/__init__.py
airless/google/cloud/storage/hook/datalake.py
airless/google/cloud/storage/hook/storage.py
airless/google/cloud/storage/operator/__init__.py
airless/google/cloud/storage/operator/error.py
airless/google/cloud/storage/operator/file.py
airless/google/cloud/storage/operator/ftp.py
airless/google/cloud/storage/operator/storage.py
airless_google_cloud_storage-0.4.1.dist-info/METADATA
airless_google_cloud_storage-0.4.1.dist-info/WHEEL
airless_google_cloud_storage-0.4.1.dist-info/top_level.txt
airless_google_cloud_storage-0.4.1.dist-info/RECORD
