Metadata-Version: 2.4
Name: airless-google-cloud-storage
Version: 0.4.1
Summary: Airless package to work with google cloud storage
License: MIT License
Project-URL: Homepage, https://github.com/astercapital/airless
Project-URL: Bug Tracker, https://github.com/astercapital/airless/issues
Requires-Python: >=3.9
Requires-Dist: google-cloud-storage<3.0.0,>=2.17.0
Requires-Dist: ndjson<0.4.0,>=0.3.0
Requires-Dist: pyarrow<=20.0.0,>=11.0.0
Requires-Dist: deprecation<2.2.0,>=2.1.0
Requires-Dist: airless-core>=0.2.5
Requires-Dist: airless-google-cloud-core>=0.1.0
